LICENSE.txt
MANIFEST.in
README.rst
setup.py
bin/pds
bin/pds.cmd
examples/clients.json
examples/compilerTest.json
examples/errorModule.py
examples/fakeActivityScore.py
examples/fakeActivityScoreStreamed.py
examples/groupModule.py
examples/queries.json
examples/scopes.json
examples/types.json
examples/wifiCounter.py
examples/wifiFilter.py
pdsapi/__init__.py
pdsapi/clients.py
pdsapi/data.py
pdsapi/groups.py
pdsapi/jobs.py
pdsapi/modules.py
pdsapi/nodes.py
pdsapi/oauth.py
pdsapi/pds.py
pdsapi/profile.py
pdsapi/queries.py
pdsapi/resource.py
pdsapi/scopes.py
pdsapi/session.py
pdsapi/types.py
pdsapi/upload.py
pdsapi/users.py
pdsapi/utils.py
pdscli/__init__.py
pdscli/clidriver.py
pdscli/load_users.py
pdscli.egg-info/PKG-INFO
pdscli.egg-info/SOURCES.txt
pdscli.egg-info/dependency_links.txt
pdscli.egg-info/requires.txt
pdscli.egg-info/top_level.txt
pdscli/commands/__init__.py
pdscli/commands/config.py
pdscli/commands/data.py
pdscli/commands/exceptions.py
pdscli/commands/groups.py
pdscli/commands/jobs.py
pdscli/commands/login.py
pdscli/commands/modules.py
pdscli/commands/resource.py
pdscli/commands/utils.py