Metadata-Version: 1.1
Name: pdscli
Version: 0.1.4
Summary: Command Line Environment for the Personal Data Store.
Home-page: http://youtechnology.github.io/pdsServer/doc/commandLine/
Author: Sean Fitts
Author-email: sean@you.tc
License: Apache License 2.0
Platform: UNKNOWN
Classifier: Development Status :: 3 - Alpha
Classifier: Intended Audience :: Developers
Classifier: Intended Audience :: System Administrators
Classifier: Natural Language :: English
Classifier: License :: OSI Approved :: Apache Software License
Classifier: Programming Language :: Python
Classifier: Programming Language :: Python :: 2.7
